ir_ml/__init__.py
ir_ml/ir_ml.py
ir_serverId/__init__.py
ir_serverId/ir_serverId.py
ir_wrangler/__init__.py
ir_wrangler/ir_wrangler.py
irmagic-0.1.0.dist-info/DESCRIPTION.rst
irmagic-0.1.0.dist-info/METADATA
irmagic-0.1.0.dist-info/RECORD
irmagic-0.1.0.dist-info/WHEEL
irmagic-0.1.0.dist-info/metadata.json
irmagic-0.1.0.dist-info/top_level.txt
