Metadata-Version: 2.0
Name: irmagic
Version: 0.1.0
Summary: Intelligent Reliability Platform
Home-page: https://github.com/pypa/sampleproject
Author: MindArt
Author-email: mike.malloy.2004@gmail.com
License: UNKNOWN
Keywords: pyspark,wrangling
Platform: UNKNOWN
Classifier: Development Status :: 3 - Alpha
Classifier: Intended Audience :: Developers
Classifier: Topic :: Software Development :: Build Tools
Classifier: License :: OSI Approved :: MIT License
Classifier: Programming Language :: Python :: 2
Classifier: Programming Language :: Python :: 2.7
Classifier: Programming Language :: Python :: 3
Classifier: Programming Language :: Python :: 3.4
Classifier: Programming Language :: Python :: 3.5
Classifier: Programming Language :: Python :: 3.6
